tecton_gen_ai/__init__.py
tecton_gen_ai/_version.py
tecton_gen_ai/checkpoint.py
tecton_gen_ai/constants.py
tecton_gen_ai/deco.py
tecton_gen_ai/fco.py
tecton_gen_ai/knowledge.py
tecton_gen_ai/realtime_utils.py
tecton_gen_ai/agent/__init__.py
tecton_gen_ai/agent/client.py
tecton_gen_ai/agent/service.py
tecton_gen_ai/integrations/__init__.py
tecton_gen_ai/integrations/lancedb.py
tecton_gen_ai/integrations/langchain.py
tecton_gen_ai/integrations/llama_index.py
tecton_gen_ai/testing/__init__.py
tecton_gen_ai/testing/fixtures.py
tecton_gen_ai/testing/interactive.py
tecton_gen_ai/testing/mocks.py
tecton_gen_ai/testing/utils.py
tecton_gen_ai/utils/__init__.py
tecton_gen_ai/utils/_extra_attrs.py
tecton_gen_ai/utils/_internal.py
tecton_gen_ai/utils/config_wrapper.py
tecton_gen_ai/utils/convert.py
tecton_gen_ai/utils/hashing.py
tecton_gen_ai/utils/log.py
tecton_gen_ai/utils/tecton_utils.py
tecton_gen_ai-0.0.1.dist-info/METADATA
tecton_gen_ai-0.0.1.dist-info/WHEEL
tecton_gen_ai-0.0.1.dist-info/entry_points.txt
tecton_gen_ai-0.0.1.dist-info/RECORD
